<TEXT><KEY>2014061902</KEY><DEV></DEV><SERVICE>Rewards from Grand Prix event</SERVICE></TEXT><TEXT><KEY>2014061901</KEY><DEV></DEV><SERVICE>Play to Win Event  Rewards items.</SERVICE></TEXT><TEXT><KEY>200400</KEY><DEV></DEV><SERVICE>Do you want to receive all of the items on this page? \n*Please take note of the time limit for Mascot.</SERVICE></TEXT><TEXT><KEY>200300</KEY><DEV></DEV><SERVICE>Passcode change</SERVICE></TEXT><TEXT><KEY>200223</KEY><DEV></DEV><SERVICE>You have completed the mission. /n Rewards will be in your Pangya mailbox.</SERVICE></TEXT><TEXT><KEY>200222</KEY><DEV></DEV><SERVICE>Rewards will be presented to you in your Pangya mailbox.</SERVICE></TEXT><TEXT><KEY>200221</KEY><DEV></DEV><SERVICE>Play in West Wiz, Wiz Wiz, White Wiz and Wiz City</SERVICE></TEXT><TEXT><KEY>200220</KEY><DEV></DEV><SERVICE>Used Arin Comets \n %d  / %d comets</SERVICE></TEXT><TEXT><KEY>200219</KEY><DEV></DEV><SERVICE>Use 30 Arin Comets</SERVICE></TEXT><TEXT><KEY>200218</KEY><DEV></DEV><SERVICE>Hole count  \n%d / %d times</SERVICE></TEXT><TEXT><KEY>200217</KEY><DEV></DEV><SERVICE>Play 18 holes twice with Arin.</SERVICE></TEXT><TEXT><KEY>200216</KEY><DEV></DEV><SERVICE>Attendance  \n%d / %d days</SERVICE></TEXT><TEXT><KEY>200215</KEY><DEV></DEV><SERVICE>Login for 5 days</SERVICE></TEXT><TEXT><KEY>200214</KEY><DEV></DEV><SERVICE>Pangya Shot success rate \n%d / %d times</SERVICE></TEXT><TEXT><KEY>200213</KEY><DEV></DEV><SERVICE>Hit Pangya 500 times</SERVICE></TEXT><TEXT><KEY>200212</KEY><DEV></DEV><SERVICE>Can you see this pretty shiny circle?\nIt was a wonderful magic show. \nThank you everyone for your help. I am so happy !</SERVICE></TEXT><TEXT><KEY>200211</KEY><DEV></DEV><SERVICE>Finally the magic circle is completed.\nIt is so beautiful !</SERVICE></TEXT><TEXT><KEY>200210</KEY><DEV></DEV><SERVICE>Mission clear !\nI can feel the magic power arising.</SERVICE></TEXT><TEXT><KEY>200209</KEY><DEV></DEV><SERVICE>The circle shown here can summon the gift of magic power.\nBut I need you to clear a mission. It shoudn't be too difficult.</SERVICE></TEXT><TEXT><KEY>200208</KEY><DEV></DEV><SERVICE>This year, I'm going to perform a magic show. \nI'll need your help.</SERVICE></TEXT><TEXT><KEY>200207</KEY><DEV></DEV><SERVICE>Hello. Thank you everyone for coming. \nThank you for being my audience.</SERVICE></TEXT><TEXT><KEY>200206</KEY><DEV></DEV><SERVICE>Wow ~ ! \nYou have collected all the ticket pieces. \nQuckily enter as the Magic Show is about to start very soon.</SERVICE></TEXT><TEXT><KEY>200205</KEY><DEV></DEV><SERVICE>You can get a magic show ticket \nby collecting the pieces.</SERVICE></TEXT><TEXT><KEY>200204</KEY><DEV></DEV><SERVICE>I'm sorry. \nYou do not have an admission ticket.</SERVICE></TEXT><TEXT><KEY>200203</KEY><DEV></DEV><SERVICE>Welcome to Arin's Magical Show ! \nDo you have a ticket?</SERVICE></TEXT><TEXT><KEY>200202</KEY><DEV></DEV><SERVICE>Have a good time !</SERVICE></TEXT><TEXT><KEY>200201</KEY><DEV></DEV><SERVICE>Congratulations, you have a ticket ! \nYou may enter now.</SERVICE></TEXT><TEXT><KEY>200200</KEY><DEV></DEV><SERVICE>Welcome to Arin's Magical Show ! \nDo you have a ticket?</SERVICE></TEXT><TEXT><KEY>200112</KEY><DEV></DEV><SERVICE>For giving %s (%d) to character, you have recieved a special effect.</SERVICE></TEXT><TEXT><KEY>200111</KEY><DEV></DEV><SERVICE>For giving %s (%d) to character, you have recieved a special item.</SERVICE></TEXT><TEXT><KEY>200110</KEY><DEV></DEV><SERVICE>This is too small, \n we need to get a bigger space.</SERVICE></TEXT><TEXT><KEY>200109</KEY><DEV></DEV><SERVICE>Feeling something in my heart. \n I don’t know what is it.</SERVICE></TEXT><TEXT><KEY>200108</KEY><DEV></DEV><SERVICE>Accuracy is important. \n And shooting too.</SERVICE></TEXT><TEXT><KEY>200107</KEY><DEV></DEV><SERVICE>Calm down to make\n the right decision.</SERVICE></TEXT><TEXT><KEY>200106</KEY><DEV></DEV><SERVICE>Don’t forget that feeling \n when you hit Pangya.</SERVICE></TEXT><TEXT><KEY>200105</KEY><DEV></DEV><SERVICE>This is my experience as the \n Lunar Tomb’s Captain!</SERVICE></TEXT><TEXT><KEY>200104</KEY><DEV></DEV><SERVICE>Listen my song. \n Don’t you like my voice?</SERVICE></TEXT><TEXT><KEY>200103</KEY><DEV></DEV><SERVICE>Too many pumpkins around \n in Halloween.</SERVICE></TEXT><TEXT><KEY>200102</KEY><DEV></DEV><SERVICE>Spooky furniture. \n Would you want it?</SERVICE></TEXT><TEXT><KEY>200101</KEY><DEV></DEV><SERVICE>Try on my new clothes ! \n Do you like them?</SERVICE></TEXT><TEXT><KEY>200100</KEY><DEV></DEV><SERVICE>You're invited to my \n Magic Show next month.</SERVICE></TEXT><TEXT><KEY>200001</KEY><DEV></DEV><SERVICE>No Stats</SERVICE></TEXT><TEXT><KEY>100502</KEY><DEV></DEV><SERVICE>Check <font color="#ff0000">My Room</font> for the prize.</SERVICE></TEXT><TEXT><KEY>100501</KEY><DEV></DEV><SERVICE>Scratch Result</SERVICE></TEXT><TEXT><KEY>100432</KEY><DEV></DEV><SERVICE>This slot is currently disabled.</SERVICE></TEXT><TEXT><KEY>100431</KEY><DEV></DEV><SERVICE>Special accessory required to activate this slot.</SERVICE></TEXT><TEXT><KEY>100430</KEY><DEV></DEV><SERVICE>%s required.</SERVICE></TEXT><TEXT><KEY>100429</KEY><DEV></DEV><SERVICE>Confirm to unequip card to\n%s slot?</SERVICE></TEXT><TEXT><KEY>100428</KEY><DEV></DEV><SERVICE>Confirm to equip card to\n%s slot?</SERVICE></TEXT><TEXT><KEY>100427</KEY><DEV></DEV><SERVICE>Bonus</SERVICE></TEXT><TEXT><KEY>100426</KEY><DEV></DEV><SERVICE>Does not use Card Patcher.</SERVICE></TEXT><TEXT><KEY>100425</KEY><DEV></DEV><SERVICE>Uses 1 Card Patcher.</SERVICE></TEXT><TEXT><KEY>100424</KEY><DEV></DEV><SERVICE><%s> Cards\nunequipped.</SERVICE></TEXT><TEXT><KEY>100423</KEY><DEV></DEV><SERVICE><%s> Cards\nequipped.</SERVICE></TEXT><TEXT><KEY>100422</KEY><DEV></DEV><SERVICE><%s> slot\nhas expanded.</SERVICE></TEXT><TEXT><KEY>100421</KEY><DEV></DEV><SERVICE>After you have reached this point,\nyou will get Control and Accuracy -1 penalty.</SERVICE></TEXT><TEXT><KEY>100420</KEY><DEV></DEV><SERVICE>Power slot bonus depends on rank.\nNext Bonus Rank : [%s] </SERVICE></TEXT><TEXT><KEY>100419</KEY><DEV></DEV><SERVICE>Every rank level-up\nyou will get +1 Power Slot Bonus\nand 1 Power Penalty\ndecrease.</SERVICE></TEXT><TEXT><KEY>100418</KEY><DEV></DEV><SERVICE>Spend [%d] TP to\nexpand the slot?</SERVICE></TEXT><TEXT><KEY>100417</KEY><DEV></DEV><SERVICE>[%s] Achievement done.</SERVICE></TEXT><TEXT><KEY>100416</KEY><DEV></DEV><SERVICE>[%s] Reached</SERVICE></TEXT><TEXT><KEY>100415</KEY><DEV></DEV><SERVICE>Current TP : %d</SERVICE></TEXT><TEXT><KEY>100414</KEY><DEV></DEV><SERVICE>Required TP : %d</SERVICE></TEXT><TEXT><KEY>100413</KEY><DEV></DEV><SERVICE>[%d] more Slot count is required.</SERVICE></TEXT><TEXT><KEY>100412</KEY><DEV></DEV><SERVICE>Over [%d] Power Points\n[-%d] Points Penalty</SERVICE></TEXT><TEXT><KEY>100411</KEY><DEV></DEV><SERVICE>\nCard : %d</SERVICE></TEXT><TEXT><KEY>100410</KEY><DEV></DEV><SERVICE>\nParts : %d</SERVICE></TEXT><TEXT><KEY>100409</KEY><DEV></DEV><SERVICE>\nCharacter Mastery : %d</SERVICE></TEXT><TEXT><KEY>100408</KEY><DEV></DEV><SERVICE>Special Card : %d</SERVICE></TEXT><TEXT><KEY>100407</KEY><DEV></DEV><SERVICE>NPC Card : %d</SERVICE></TEXT><TEXT><KEY>100406</KEY><DEV></DEV><SERVICE>Character Primary Ability</SERVICE></TEXT><TEXT><KEY>100405</KEY><DEV></DEV><SERVICE>*After [%d] Power points you will get\n-1 Control and Accuracy points penalty.</SERVICE></TEXT><TEXT><KEY>100404</KEY><DEV></DEV><SERVICE>Do you want to downgrade the \n[%s ability]?</SERVICE></TEXT><TEXT><KEY>100403</KEY><DEV></DEV><SERVICE>To upgrade the [%s ability]\nyou need [%d Pangs].\nConfirm upgrading?</SERVICE></TEXT><TEXT><KEY>100402</KEY><DEV></DEV><SERVICE><%s> stat\nhas downgraded.</SERVICE></TEXT><TEXT><KEY>100401</KEY><DEV></DEV><SERVICE><%s> stat\nhas upgraded.</SERVICE></TEXT><TEXT><KEY>100301</KEY><DEV></DEV><SERVICE>"It shows the predicted trajectory of your comet due to the wind.
The Miracle Sign's effect is automatically triggered when your comet is on the green.
When using these functions, you will receive 30% less pangs.
Pang deduction penalty applies only to players ranked from Junior E to Infinity Legend A"</SERVICE></TEXT><TEXT><KEY>100201</KEY><DEV></DEV><SERVICE>(Short Game)</SERVICE></TEXT><TEXT><KEY>100113</KEY><DEV></DEV><SERVICE>Insufficent Pangs.\nPlease try again later.</SERVICE></TEXT><TEXT><KEY>100112</KEY><DEV></DEV><SERVICE>%d Pang is required.
</SERVICE></TEXT><TEXT><KEY>100111</KEY><DEV></DEV><SERVICE>Please select the quantity.</SERVICE></TEXT><TEXT><KEY>100110</KEY><DEV></DEV><SERVICE>You already have over 20000 TP.\nPlease retry after you spend your TP.</SERVICE></TEXT><TEXT><KEY>100109</KEY><DEV></DEV><SERVICE>%d mileage earned.</SERVICE></TEXT><TEXT><KEY>100107</KEY><DEV></DEV><SERVICE>\\c0xffff0000\\cCongratulations.\\c0xff000000\\c\nYou earned extra %d mileage! Success!\nTotal %d mileage earned.</SERVICE></TEXT><TEXT><KEY>100106</KEY><DEV></DEV><SERVICE>\\c0xffff0000\\c[Warning]\\c0xff000000\\c This process can not be undone.</SERVICE></TEXT><TEXT><KEY>100105</KEY><DEV></DEV><SERVICE>Are you sure to recycle?</SERVICE></TEXT><TEXT><KEY>100104</KEY><DEV></DEV><SERVICE>\\c0xffff0000\\c[Warning]\\c0xff000000\\c Rare cards are included.</SERVICE></TEXT><TEXT><KEY>100103</KEY><DEV></DEV><SERVICE>\\c0xffff0000\\c[Warning]\\c0xff000000\\c Club Modification kit included.</SERVICE></TEXT><TEXT><KEY>100102</KEY><DEV></DEV><SERVICE>\\c0xffff0000\\c[Warning]\\c0xff000000\\c Rare items are included.</SERVICE></TEXT><TEXT><KEY>100101</KEY><DEV></DEV><SERVICE>\\c0xffff0000\\c[Warning]\\c0xff000000\\c Self-design items are included.</SERVICE></TEXT><TEXT><KEY>100100</KEY><DEV></DEV><SERVICE>Would like to recycle your item and get mileage?</SERVICE></TEXT><TEXT><KEY>100031</KEY><DEV></DEV><SERVICE>Wow! Congratulations! You earned TP Points~\nYou can use your TP points while combining,merging and upgrading your character mastery.</SERVICE></TEXT><TEXT><KEY>100022</KEY><DEV></DEV><SERVICE>Your mileage is less than 1000.\nYou can get more mileage by recycling the better items.</SERVICE></TEXT><TEXT><KEY>100021</KEY><DEV></DEV><SERVICE>Ummm… As you know many a mickle makes a muckle…\nWhy don't you be more brave and try more?</SERVICE></TEXT><TEXT><KEY>100012</KEY><DEV></DEV><SERVICE>Umm… Do you have any items to recyle?\nPlease be careful to not recycle your RARE items!</SERVICE></TEXT><TEXT><KEY>100011</KEY><DEV></DEV><SERVICE>Emm… Sometimes you can get extra mileage.\nThis depends on your luck. Good luck!</SERVICE></TEXT><TEXT><KEY>100002</KEY><DEV></DEV><SERVICE>You can get TP points when you have 1000 Mileage points.\nYou can get mileage when you recycle the items.</SERVICE></TEXT><TEXT><KEY>100001</KEY><DEV></DEV><SERVICE>Ooooh, you can get TP points by recycling the items.\nDo you have any items to recyle?</SERVICE></TEXT><TEXT><KEY>95003</KEY><DEV></DEV><SERVICE>"If you already have a Decoration item\nit will be dissapear.\nConfirm?"</SERVICE></TEXT><TEXT><KEY>95002</KEY><DEV></DEV><SERVICE>You can combine and create new items with Cadie's Cauldron.\nSo lets create new items!</SERVICE></TEXT><TEXT><KEY>95001</KEY><DEV></DEV><SERVICE>※ Important Notice about Auto Calipers\n\n1) If you already used some of the Auto Calipers you can not refund the remaining ones.\n2) The items you get by exchanging the Auto Caliopers can not be refunded.\n\nConfirm the combination process?</SERVICE></TEXT><TEXT><KEY>90007</KEY><DEV></DEV><SERVICE>Adjust the brightness.</SERVICE></TEXT><TEXT><KEY>90006</KEY><DEV></DEV><SERVICE>Turn ON/OFF the Anti-aliasing.</SERVICE></TEXT><TEXT><KEY>90005</KEY><DEV></DEV><SERVICE>Turn ON/OFF the Contrast.</SERVICE></TEXT><TEXT><KEY>90004</KEY><DEV></DEV><SERVICE>Turn ON/OFF the Rim Light.</SERVICE></TEXT><TEXT><KEY>90003</KEY><DEV></DEV><SERVICE>Turn ON/OFF the DOF.</SERVICE></TEXT><TEXT><KEY>90002</KEY><DEV></DEV><SERVICE>Turn ON/OFF the HDR Star Effect.</SERVICE></TEXT><TEXT><KEY>90001</KEY><DEV></DEV><SERVICE>Turn ON/OFF the HDR Effect</SERVICE></TEXT><TEXT><KEY>60005</KEY><DEV></DEV><SERVICE>You cannot use Replay Tape in the Lounge.</SERVICE></TEXT><TEXT><KEY>60004</KEY><DEV></DEV><SERVICE>Your gifts have arrived.\nCheck your <font color="#ff0000">Mailbox</font>.</SERVICE></TEXT><TEXT><KEY>60003</KEY><DEV></DEV><SERVICE>You have a new message.</SERVICE></TEXT><TEXT><KEY>50005</KEY><DEV></DEV><SERVICE>Not enough Pang to play BIG mode</SERVICE></TEXT><TEXT><KEY>50004</KEY><DEV></DEV><SERVICE>Check your received items in "My Room"</SERVICE></TEXT><TEXT><KEY>50003</KEY><DEV></DEV><SERVICE>Items Won.</SERVICE></TEXT><TEXT><KEY>50002</KEY><DEV></DEV><SERVICE>You didn't win anything.</SERVICE></TEXT><TEXT><KEY>50001</KEY><DEV></DEV><SERVICE>You have Insufficient Pang</SERVICE></TEXT><TEXT><KEY>40004</KEY><DEV></DEV><SERVICE>The comet has been blessed by %s's Animal Power and flies with precision.</SERVICE></TEXT><TEXT><KEY>40003</KEY><DEV></DEV><SERVICE>The comet has been blessed by %s's ring and flies with accuracy.</SERVICE></TEXT><TEXT><KEY>40002</KEY><DEV></DEV><SERVICE>Power transfer 100%</SERVICE></TEXT><TEXT><KEY>40001</KEY><DEV></DEV><SERVICE>Earned additional Pangya Combo gauge</SERVICE></TEXT><TEXT><KEY>30039</KEY><DEV></DEV><SERVICE>You need to be in the Multiplay mode to enter Lounge.</SERVICE></TEXT><TEXT><KEY>30037</KEY><DEV></DEV><SERVICE>Course : SPECIAL</SERVICE></TEXT><TEXT><KEY>30036</KEY><DEV></DEV><SERVICE>You can have up to 50 Grand Prix tickets and you can acquire more by completing multiplayer mode and logging in.</SERVICE></TEXT><TEXT><KEY>30035</KEY><DEV></DEV><SERVICE>Grand Prix Award Ceremony</SERVICE></TEXT><TEXT><KEY>30034</KEY><DEV></DEV><SERVICE>%s until game starts.</SERVICE></TEXT><TEXT><KEY>30033</KEY><DEV></DEV><SERVICE>%s acquired!!</SERVICE></TEXT><TEXT><KEY>30032</KEY><DEV></DEV><SERVICE>Please try again at another time.</SERVICE></TEXT><TEXT><KEY>30031</KEY><DEV></DEV><SERVICE>Special Rule +1 Penalty Stroke added</SERVICE></TEXT><TEXT><KEY>30030</KEY><DEV></DEV><SERVICE>You can now enter %s tourney.</SERVICE></TEXT><TEXT><KEY>30029</KEY><DEV></DEV><SERVICE>Class %d Tourney Completed %d%</SERVICE></TEXT><TEXT><KEY>30028</KEY><DEV></DEV><SERVICE>Tourney Skill Limit: only players with %d or higher average strokes can participate.</SERVICE></TEXT><TEXT><KEY>30027</KEY><DEV></DEV><SERVICE>Tourney Skill Limit: Only players with %d or lower average strokes can participate.</SERVICE></TEXT><TEXT><KEY>30026</KEY><DEV></DEV><SERVICE>Tourney Level Limit: Only %s to %s can participate.</SERVICE></TEXT><TEXT><KEY>30025</KEY><DEV></DEV><SERVICE>3 X Hole Cup</SERVICE></TEXT><TEXT><KEY>30024</KEY><DEV></DEV><SERVICE>2 X Hole Cup</SERVICE></TEXT><TEXT><KEY>30023</KEY><DEV></DEV><SERVICE>Special rule :</SERVICE></TEXT><TEXT><KEY>30022</KEY><DEV></DEV><SERVICE>Prize : %s</SERVICE></TEXT><TEXT><KEY>30021</KEY><DEV></DEV><SERVICE>Game Time : Start %02d:%02d End %02d:%02d</SERVICE></TEXT><TEXT><KEY>30020</KEY><DEV></DEV><SERVICE>You cannot select your equipments for equipment restricted tourney.</SERVICE></TEXT><TEXT><KEY>30019</KEY><DEV></DEV><SERVICE>Grand Prix</SERVICE></TEXT><TEXT><KEY>30018</KEY><DEV></DEV><SERVICE>%d Difficulty</SERVICE></TEXT><TEXT><KEY>30017</KEY><DEV></DEV><SERVICE>Entry Ticket : %d</SERVICE></TEXT><TEXT><KEY>30016</KEY><DEV></DEV><SERVICE>Alarm has been set, you will be notified via in-game announcement 10 minutes before the tourney.</SERVICE></TEXT><TEXT><KEY>30015</KEY><DEV></DEV><SERVICE>You must finish progressing %s to enter.</SERVICE></TEXT><TEXT><KEY>30014</KEY><DEV></DEV><SERVICE>%d : %d %s entry has started, please enter the waiting room now to participate.</SERVICE></TEXT><TEXT><KEY>30013</KEY><DEV></DEV><SERVICE>Entry time alarm has been set.</SERVICE></TEXT><TEXT><KEY>30012</KEY><DEV></DEV><SERVICE>(If you previously had an alarm set up, recent alarm will replace it.)</SERVICE></TEXT><TEXT><KEY>30011</KEY><DEV></DEV><SERVICE>You cannot enter at this time.\nWould you like to set an alarm for the entry time?</SERVICE></TEXT><TEXT><KEY>30010</KEY><DEV></DEV><SERVICE>%d tickets will be consumed when participating in the tourney.\nTickets will be used when the tourney starts.)</SERVICE></TEXT><TEXT><KEY>30009</KEY><DEV></DEV><SERVICE>Game has already ended.</SERVICE></TEXT><TEXT><KEY>30008</KEY><DEV></DEV><SERVICE>Game has already started.</SERVICE></TEXT><TEXT><KEY>30007</KEY><DEV></DEV><SERVICE>You do not have the required ticket.</SERVICE></TEXT><TEXT><KEY>30006</KEY><DEV></DEV><SERVICE>You do not have the required equipment.</SERVICE></TEXT><TEXT><KEY>30005</KEY><DEV></DEV><SERVICE>Please check the rules and restrictions of the tourney.</SERVICE></TEXT><TEXT><KEY>30004</KEY><DEV></DEV><SERVICE>Your average stokes are lower than the recommended level.\nThis mode might be too easy for you.\n\nYou can look at your average strokes in "My Profile>Advanced"</SERVICE></TEXT><TEXT><KEY>30003</KEY><DEV></DEV><SERVICE>Your average strokes are higher than the recommended level.\nThis mode might be too difficult for you to participate.\n\nYou can look at your average strokes in "My Profile>Advanced".</SERVICE></TEXT><TEXT><KEY>30002</KEY><DEV></DEV><SERVICE>Your level is too low to participate.</SERVICE></TEXT><TEXT><KEY>30001</KEY><DEV></DEV><SERVICE>Your level is too high to participate.</SERVICE></TEXT><TEXT><KEY>6006</KEY><DEV></DEV><SERVICE>Scratchy Card system is under maintenance. Sorry for the inconvenience.</SERVICE></TEXT><TEXT><KEY>6005</KEY><DEV></DEV><SERVICE>Event Scratchy system is under maintenance. Sorry for the inconvenience.</SERVICE></TEXT><TEXT><KEY>6004</KEY><DEV></DEV><SERVICE>Recycle system is under maintenance. Sorry for the inconvenience.</SERVICE></TEXT><TEXT><KEY>6003</KEY><DEV></DEV><SERVICE>Card system is under maintenance. Sorry for the inconvenience.</SERVICE></TEXT><TEXT><KEY>6002</KEY><DEV></DEV><SERVICE>Character Mastery system is under maintenance. Sorry for the inconvenience.</SERVICE></TEXT><TEXT><KEY>6001</KEY><DEV></DEV><SERVICE>90090007</SERVICE></TEXT><TEXT><KEY>102</KEY><DEV></DEV><SERVICE>Translation request: "System Error" Sorry for the inconvenience.</SERVICE></TEXT><TEXT><KEY>101</KEY><DEV></DEV><SERVICE>Disconnected from server due to network problems (socked error: %d)</SERVICE></TEXT>